alphatools/__init__.py
alphatools/alphatools.py
alphatools/fundamentals/__init__.py
alphatools/fundamentals/fundamentals.py
alphatools/fundamentals/make_fundamentals.py
alphatools/ics/__init__.py
alphatools/ics/ics_scheme.py
alphatools-0.1.dist-info/METADATA
alphatools-0.1.dist-info/RECORD
alphatools-0.1.dist-info/WHEEL
alphatools-0.1.dist-info/top_level.txt
